timezonefinderL/__init__.py
timezonefinderL/file_converter.py
timezonefinderL/functional.py
timezonefinderL/helpers.py
timezonefinderL/helpers_numba.py
timezonefinderL/hole_adr2data.bin
timezonefinderL/hole_coord_amount.bin
timezonefinderL/hole_data.bin
timezonefinderL/hole_poly_ids.bin
timezonefinderL/poly_adr2data.bin
timezonefinderL/poly_coord_amount.bin
timezonefinderL/poly_data.bin
timezonefinderL/poly_max_values.bin
timezonefinderL/poly_nr2zone_id.bin
timezonefinderL/poly_zone_ids.bin
timezonefinderL/shortcuts_adr2data.bin
timezonefinderL/shortcuts_data.bin
timezonefinderL/shortcuts_entry_amount.bin
timezonefinderL/shortcuts_unique_id.bin
timezonefinderL/timezone_names.py
timezonefinderL/timezonefinderL.py
timezonefinderL-2.0.1.dist-info/DESCRIPTION.rst
timezonefinderL-2.0.1.dist-info/METADATA
timezonefinderL-2.0.1.dist-info/RECORD
timezonefinderL-2.0.1.dist-info/WHEEL
timezonefinderL-2.0.1.dist-info/metadata.json
timezonefinderL-2.0.1.dist-info/top_level.txt
