Metadata-Version: 2.0
Name: timezonefinderL
Version: 2.0.1
Summary: Python library to look up timezone from coordinates offline. Light version of "timezonefinder".
Home-page: https://github.com/MrMinimal64/timezonefinderL
Author: J. Michelfeit
Author-email: python@michelfe.it
License: MIT licence
Keywords: timezone coordinates latitude longitude location pytzwhere tzwhere
Platform: UNKNOWN
Classifier: Development Status :: 5 - Production/Stable
Classifier: Intended Audience :: Developers
Classifier: License :: OSI Approved :: MIT License
Classifier: Operating System :: OS Independent
Classifier: Programming Language :: Python
Classifier: Programming Language :: Python :: 2
Classifier: Programming Language :: Python :: 2.7
Classifier: Programming Language :: Python :: 3
Classifier: Programming Language :: Python :: 3.3
Classifier: Programming Language :: Python :: 3.4
Classifier: Programming Language :: Python :: 3.5
Classifier: Topic :: Software Development :: Localization
Requires-Dist: numpy
